Metadata-Version: 2.1
Name: temporarycheck-csdt
Version: 0.0.0.9
Summary: This package provides a framework for organizing groups of     users and restricting access in other views and models
Home-page: UNKNOWN
Author: Sumedh Walujkar
Author-email: sumedh@umich.edu
License: UNKNOWN
Platform: UNKNOWN
